name/__init__.py
name/main.py
name_cli-0.1.0.dist-info/METADATA
name_cli-0.1.0.dist-info/WHEEL
name_cli-0.1.0.dist-info/entry_points.txt
name_cli-0.1.0.dist-info/top_level.txt
name_cli-0.1.0.dist-info/RECORD
