Metadata-Version: 2.4
Name: name-cli
Version: 0.1.0
Summary: Simple CLI to store and display your name
Home-page: https://github.com/veranyagaka/name-cli
Author: Vera Nyagaka
Author-email: nyagakavera@gmail.com
Classifier: Programming Language :: Python :: 3
Classifier: License :: OSI Approved :: MIT License
Classifier: Operating System :: OS Independent
Requires-Python: >=3.7
